{"sections":{"hero":{"type":"collection-image-with-title","settings":{"show_title":false,"show_description":false,"flex_align":"align--middle-center","color_scheme":"scheme-2","show_text_background":false,"show_image":false,"banner_layout":"overlay","height":"two-fifty-height-hero","mobile_height":"two-fifty-height-hero--mobile","overlay_opacity":0,"show_overlay_text":false,"padding_top":0,"padding_bottom":0}},"section_video_VpLNCL":{"type":"section-video","settings":{"video":"shopify:\/\/files\/videos\/designer-boys-platinum-canvas-art.mp4","show_video_popup":false,"video_popup_social":"https:\/\/www.youtube.com\/watch?v=_9VUPq3SxOc","title":"{{ collection.title }}","heading_font_size":"heading-large","text":"<p>{{ collection.description }}<\/p>","text_font_size":"body-medium","flex_align":"align--middle-center","link_text":"","link":"","button_type":"btn--primary","button_size":"","button_style":"btn--solid","show_arrow":false,"image":"shopify:\/\/shop_images\/designer-boys-platinum-canvas-art.webp","desktop_height":"screen-height-one-half","mobile_height":"screen-height-one-third--mobile","width":"wrapper--full","color_scheme":"scheme-9","show_text_background":false,"color":"","overlay_opacity":0,"show_overlay_text":false,"padding_top":0,"padding_bottom":0,"heading_tag":"h1"}},"subcollections":{"type":"subcollections","disabled":true,"settings":{"subcollection_layout":"grid","subcollection_description":false,"select_image":"collection","color_scheme":"scheme-2","color":"#ffffff","bg_color":"","padding_top":20,"padding_bottom":20}},"main":{"type":"collection","blocks":{"featured_image_cWNKjU":{"type":"featured_image","disabled":true,"settings":{"featured_image":"shopify:\/\/shop_images\/designerboys-artwork-mercury-abstract.jpg","position":5,"featured_heading":"Mercury Abstract Collection","heading_font_size":"heading-medium","featured_text":"","featured_button_text":"Shop the Collection","featured_button_link":"https:\/\/designerboysart.myshopify.com\/collections\/artwork\/subject-abstract","button_type":"btn--primary","button_size":"","button_style":"btn--text","show_arrow":false,"featured_color_text":"#ffffff","featured_color_overlay":"#222222","featured_overlay_opacity":0,"heading_tag":"automatic"}}},"block_order":["featured_image_cWNKjU"],"settings":{"enable_sort":true,"enable_filters":true,"filter_layout":"inline-closed","default_open":false,"collection_linklist":"type","grid":4,"grid_mobile":"2","products_per_page":48,"color_scheme":"scheme-2","padding_top":0,"padding_bottom":50}},"section_highlights_M377Am":{"type":"section-highlights","blocks":{"highlight_Lcq7ja":{"type":"highlight","settings":{"heading":"All","url":"shopify:\/\/collections\/all-art","color":"#212121","bg_color":"#f4f4f4","border_color":"#f4f4f4"}},"highlight_ffDLHj":{"type":"highlight","settings":{"heading":"Prints","url":"shopify:\/\/collections\/print-art","color":"#212121","bg_color":"#f4f4f4","border_color":"#f4f4f4"}},"highlight_DnV38X":{"type":"highlight","settings":{"heading":"Kids","url":"shopify:\/\/collections\/all-art","color":"#212121","bg_color":"#f4f4f4","border_color":"#f4f4f4"}},"highlight_BAMgJ8":{"type":"highlight","settings":{"heading":"Textural","url":"shopify:\/\/collections\/all-art","color":"#212121","bg_color":"#f4f4f4","border_color":"#f4f4f4"}}},"block_order":["highlight_Lcq7ja","highlight_ffDLHj","highlight_DnV38X","highlight_BAMgJ8"],"settings":{"style":"button","grid":6,"heading":"{{ collection.metafields.custom.seo_footer_title.value }}","description":"{{ collection.metafields.custom.seo_footer_description | metafield_tag }}","heading_position":"text-left","heading_font_size":"heading-x-small","text_font_size":"body-x-small","width":"wrapper--full-padded","layout_mobile":"2","color_scheme":"","padding_top":30,"padding_bottom":80,"heading_tag":"h2"}}},"order":["hero","section_video_VpLNCL","subcollections","main","section_highlights_M377Am"]}